Products.CMFQuickInstallerTool-4.0.3-py2.7-nspkg.pth
Products/CMFQuickInstallerTool/InstalledProduct.py
Products/CMFQuickInstallerTool/QuickInstallerTool.py
Products/CMFQuickInstallerTool/__init__.py
Products/CMFQuickInstallerTool/configure.zcml
Products/CMFQuickInstallerTool/events.py
Products/CMFQuickInstallerTool/testing.py
Products/CMFQuickInstallerTool/tool.gif
Products/CMFQuickInstallerTool/tool.png
Products/CMFQuickInstallerTool/utils.py
Products/CMFQuickInstallerTool/forms/install_products_form.zpt
Products/CMFQuickInstallerTool/forms/installed_product_overview.zpt
Products/CMFQuickInstallerTool/interfaces/__init__.py
Products/CMFQuickInstallerTool/interfaces/installable.py
Products/CMFQuickInstallerTool/interfaces/portal_quickinstaller.py
Products/CMFQuickInstallerTool/profiles/default/metadata.xml
Products/CMFQuickInstallerTool/profiles/default/toolset.xml
Products/CMFQuickInstallerTool/profiles/uninstall/toolset.xml
Products/CMFQuickInstallerTool/tests/__init__.py
Products/CMFQuickInstallerTool/tests/actions.txt
Products/CMFQuickInstallerTool/tests/install.txt
Products/CMFQuickInstallerTool/tests/metadata.xml
Products/CMFQuickInstallerTool/tests/profiles.txt
Products/CMFQuickInstallerTool/tests/testQuickInstallerTool.py
Products/CMFQuickInstallerTool/tests/testSetup.py
Products/CMFQuickInstallerTool/tests/test_browser.py
Products/CMFQuickInstallerTool/tests/test_doctests.py
Products/CMFQuickInstallerTool/tests/test_install.py
Products/CMFQuickInstallerTool/tests/test_upgrades1.zcml
Products/CMFQuickInstallerTool/tests/test_upgrades2.zcml
Products/CMFQuickInstallerTool/tests/profiles/test/actions.xml
Products/CMFQuickInstallerTool/tests/profiles/test/propertiestool.xml
Products/CMFQuickInstallerTool/tests/profiles/test_uninstall/propertiestool.xml
Products.CMFQuickInstallerTool-4.0.3.dist-info/METADATA
Products.CMFQuickInstallerTool-4.0.3.dist-info/WHEEL
Products.CMFQuickInstallerTool-4.0.3.dist-info/namespace_packages.txt
Products.CMFQuickInstallerTool-4.0.3.dist-info/top_level.txt
Products.CMFQuickInstallerTool-4.0.3.dist-info/RECORD
