Metadata-Version: 2.1
Name: Products.CMFQuickInstallerTool
Version: 4.0.3
Summary: A facility for comfortable activation/deactivation of CMF compliant add ons for Zope.
Home-page: https://pypi.org/project/Products.CMFQuickInstallerTool
Author: Philipp Auersperg
Author-email: plone-developers@lists.sourceforge.net
Maintainer: Hanno Schlichting
Maintainer-email: hannosch@plone.org
License: GPL
Keywords: Zope CMF Plone quickinstall install activation
Platform: UNKNOWN
Classifier: Development Status :: 6 - Mature
Classifier: Framework :: Plone
Classifier: Framework :: Plone :: 5.2
Classifier: Framework :: Zope2
Classifier: Framework :: Zope :: 4
Classifier: License :: OSI Approved :: GNU General Public License (GPL)
Classifier: Programming Language :: Python
Classifier: Programming Language :: Python :: 2.7
Classifier: Programming Language :: Python :: 3.6
Classifier: Programming Language :: Python :: 3.7
Classifier: Programming Language :: Python :: 3.8
Requires-Dist: setuptools
Requires-Dist: six
Requires-Dist: zope.annotation
Requires-Dist: zope.component
Requires-Dist: zope.i18nmessageid
Requires-Dist: zope.interface
Requires-Dist: Products.CMFCore
Requires-Dist: Products.ExternalMethod
Requires-Dist: Products.GenericSetup (>=1.8.1)
Requires-Dist: Acquisition
Requires-Dist: DateTime
Requires-Dist: Zope2
Provides-Extra: test
Requires-Dist: zope.testing ; extra == 'test'
Requires-Dist: plone.app.testing ; extra == 'test'
Requires-Dist: plone.protect (>=2.0.2) ; extra == 'test'
